{
  "parent": "minecraft:recipes/root",
  "criteria": {
    "has_log": {
      "conditions": {
        "items": [
          {
            "items": "minecraft:spruce_log"
          }
        ]
      },
      "trigger": "minecraft:inventory_changed"
    },
    "has_the_recipe": {
      "conditions": {
        "recipe": "utilitarian:utility/spruce_logs_to_trapdoors"
      },
      "trigger": "minecraft:recipe_unlocked"
    }
  },
  "requirements": [
    [
      "has_the_recipe",
      "has_log"
    ]
  ],
  "rewards": {
    "recipes": [
      "utilitarian:utility/spruce_logs_to_trapdoors"
    ]
  }
}